LICENSE.txt
MANIFEST.in
README.md
repub.conf-sample
setup.cfg
setup.py
repubmqtt/__init__.py
repubmqtt/__init__.py.orig
repubmqtt/__main__.py
repubmqtt.egg-info/PKG-INFO
repubmqtt.egg-info/SOURCES.txt
repubmqtt.egg-info/dependency_links.txt
repubmqtt.egg-info/entry_points.txt
repubmqtt.egg-info/requires.txt
repubmqtt.egg-info/top_level.txt