Metadata-Version: 1.1
Name: repubmqtt
Version: 0.2.4
Summary: RepubMQTT re-publishes MQTT messages to MQTT, RESTful or logfiles
Home-page: https://git.wrede.ca/andreas/repubmqtt/
Author: Andreas Wrede
Author-email: aew.repubmqtt@wrede.ca
License: MIT
Keywords: mqtt restful
Platform: UNKNOWN
Classifier: Development Status :: 4 - Beta
Classifier: Intended Audience :: Developers
Classifier: Topic :: Software Development :: Libraries :: Python Modules
Classifier: License :: OSI Approved :: MIT License
Classifier: Programming Language :: Python :: 2
Classifier: Programming Language :: Python :: 2.7
Classifier: Programming Language :: Python :: 3
Classifier: Programming Language :: Python :: 3.4
Classifier: Programming Language :: Python :: 3.5
Classifier: Programming Language :: Python :: 3.6
